{
  "level": [
    {
      "type": "image",
      "key": "mono",
      "url": "assets/images/mono.png",
      "overwrite": false
    },
    {
      "type": "image",
      "key": "BG",
      "url": "assets/images/BG.png",
      "overwrite": false
    },
    {
      "type": "image",
      "key": "BG2",
      "url": "assets/images/BG2.jpg",
      "overwrite": false
    },
    {
      "type": "spritesheet",
      "key": "boniatillo",
      "url": "assets/images/boniatillo.png",
      "frameWidth": 0,
      "frameHeight": 0,
      "frameMax": -1,
      "margin": 0,
      "spacing": 0
    },
    {
      "type": "atlas",
      "key": "player",
      "textureURL": "assets/atlas/player.png",
      "atlasURL": "assets/atlas/player.json",
      "format": "TEXTURE_ATLAS_JSON_HASH"
    },
    {
      "type": "atlas",
      "key": "cicken",
      "textureURL": "assets/atlas/cicken.png",
      "atlasURL": "assets/atlas/cicken.json",
      "format": "TEXTURE_ATLAS_JSON_HASH"
    },
    {
      "type": "atlas",
      "key": "devil",
      "textureURL": "assets/atlas/devil.png",
      "atlasURL": "assets/atlas/devil.json",
      "format": "TEXTURE_ATLAS_JSON_HASH"
    },
    {
      "type": "spritesheet",
      "key": "tile_set1",
      "url": "assets/tilemap/tile_set1.png",
      "frameWidth": 0,
      "frameHeight": 0,
      "frameMax": -1,
      "margin": 0,
      "spacing": 0
    },
    {
      "type": "tilemap",
      "key": "lab7",
      "url": "assets/tilemap/lab7.json",
      "format": "TILED_JSON"
    }
  ],
  "start": [{
    "type": "image",
    "key": "tap-to-start",
    "url": "assets/images/tap-to-start.png",
    "overwrite": false
  }],
  "preload": [{
    "type": "image",
    "key": "loading",
    "url": "assets/images/loading.png",
    "overwrite": false
  }],
  "meta": {
    "generated": "1510839878645",
    "app": "Phaser Editor",
    "url": "http://phasereditor.boniatillo.com",
    "version": "1.0",
    "copyright": "Arian Fornaris (c) 2015,2016"
  }
}